splitfvm/__init__.py
splitfvm/bc.py
splitfvm/boundary.py
splitfvm/cell.py
splitfvm/constants.py
splitfvm/domain.py
splitfvm/error.py
splitfvm/flux.py
splitfvm/initialize.py
splitfvm/model.py
splitfvm/refine.py
splitfvm/simulation.py
splitfvm/system.py
splitfvm/visualize.py
splitfvm/equations/__init__.py
splitfvm/equations/transport.py
SplitFVM-0.1.2.dist-info/LICENSE.md
SplitFVM-0.1.2.dist-info/METADATA
SplitFVM-0.1.2.dist-info/WHEEL
SplitFVM-0.1.2.dist-info/top_level.txt
SplitFVM-0.1.2.dist-info/RECORD
