Metadata-Version: 2.1
Name: SplitFVM
Version: 0.1.2
Summary: 1D Finite-Volume Split Newton Solver
Home-page: https://github.com/gpavanb1/SplitFVM
Author: gpavanb1
Author-email: gpavanb@gmail.com
License: MIT
Project-URL: Bug Reports, https://github.com/gpavanb1/SplitFVM/issues
Project-URL: Source, https://github.com/gpavanb1/SplitFVM/
Keywords: amr newton python finite-volume armijo optimization pseudotransient splitting
Classifier: Topic :: Scientific/Engineering :: Mathematics
Classifier: License :: OSI Approved :: MIT License
Classifier: Programming Language :: Python :: 3
Classifier: Programming Language :: Python :: 3 :: Only
License-File: LICENSE.md
Requires-Dist: numpy
Requires-Dist: numdifftools
Requires-Dist: matplotlib
Requires-Dist: splitnewton
